cpyImagingMSpec/__init__.py
cpyImagingMSpec/ims.h
cpyImagingMSpec/io.py
cpyImagingMSpec/libims_cffi.dylib
cpyImagingMSpec/metrics.py
cpyImagingMSpec/utils.py
cpyImagingMSpec/.dylibs/libgcc_s.1.dylib
cpyImagingMSpec/.dylibs/libstdc++.6.dylib
cpyImagingMSpec-0.3.2.dist-info/DESCRIPTION.rst
cpyImagingMSpec-0.3.2.dist-info/METADATA
cpyImagingMSpec-0.3.2.dist-info/metadata.json
cpyImagingMSpec-0.3.2.dist-info/RECORD
cpyImagingMSpec-0.3.2.dist-info/top_level.txt
cpyImagingMSpec-0.3.2.dist-info/WHEEL
