Metadata-Version: 2.0
Name: cpyImagingMSpec
Version: 0.3.2
Summary: utils for processing imaging mass spectrometry data
Home-page: https://github.com/alexandrovteam/cpyImagingMSpec
Author: Artem Tarasov
Author-email: artem.tarasov@embl.de
License: Apache 2.0
Platform: UNKNOWN
Classifier: Development Status :: 4 - Beta
Classifier: Intended Audience :: Science/Research
Classifier: License :: OSI Approved :: Apache Software License
Classifier: Topic :: Scientific/Engineering :: Bio-Informatics
Requires-Dist: cffi (>=1.7)
Requires-Dist: numpy (>=1.10)
Requires-Dist: pandas (>=0.18)
